MANIFEST.in
README.rst
setup.py
hy_coverage_plugin/__init__.py
hy_coverage_plugin/hy_coverage.py
hy_coverage_plugin.egg-info/PKG-INFO
hy_coverage_plugin.egg-info/SOURCES.txt
hy_coverage_plugin.egg-info/dependency_links.txt
hy_coverage_plugin.egg-info/requires.txt
hy_coverage_plugin.egg-info/top_level.txt