Metadata-Version: 1.1
Name: hy-coverage-plugin
Version: 0.0.4
Summary: coverage.py plugin for the Hy language
Home-page: https://github.com/timmartin/hy-coverage
Author: Tim Martin
Author-email: tim@asymptotic.co.uk
License: mit
Platform: UNKNOWN
Classifier: Environment :: Console
Classifier: Intended Audience :: Developers
Classifier: License :: OSI Approved :: MIT License
Classifier: Programming Language :: Python :: 3.4
Classifier: Topic :: Software Development :: Testing
Classifier: Development Status :: 3 - Alpha
